{"name": "MER R: Facility Based", "default_locale": "en", "short_code": "MER-R-Facility-FY17Q4", "external_id": "uTvHPA1zqzi", "extras": {"Period": "COP16 (FY17Q4)", "datim_sync_mer": true, "DHIS2-Dataset-Code": "MER_R_FACILITY_BASED"}, "collection_type": "Subset", "full_name": "MER Results: Facility Based", "owner": "PEPFAR", "public_access": "View", "owner_type": "Organization", "type": "Collection", "id": "MER-R-Facility-FY17Q4", "supported_locales": "en"}
{"name": "MER R: Community Based", "default_locale": "en", "short_code": "MER-R-Community-FY17Q4", "external_id": "O3VMNi8EZSV", "extras": {"Period": "COP16 (FY17Q4)", "datim_sync_mer": true, "DHIS2-Dataset-Code": "MER_R_COMMUNITY_BASED"}, "collection_type": "Subset", "full_name": "MER Results: Community Based", "owner": "PEPFAR", "public_access": "View", "owner_type": "Organization", "type": "Collection", "id": "MER-R-Community-FY17Q4", "supported_locales": "en"}
{"name": "MER R: Facility Based - DoD ONLY", "default_locale": "en", "short_code": "MER-R-Facility-DoD-FY17Q4", "external_id": "asptuHohmHt", "extras": {"Period": "COP16 (FY17Q4)", "datim_sync_mer": true, "DHIS2-Dataset-Code": "MER_R_FACILITY_BASED_DOD_ONLY"}, "collection_type": "Subset", "full_name": "MER Results: Facility Based - DoD ONLY", "owner": "PEPFAR", "public_access": "View", "owner_type": "Organization", "type": "Collection", "id": "MER-R-Facility-DoD-FY17Q4", "supported_locales": "en"}
{"name": "MER R: Community Based - DoD ONLY", "default_locale": "en", "short_code": "MER-R-Community-DoD-FY17Q4", "external_id": "Ir58H3zBKEC", "extras": {"Period": "COP16 (FY17Q4)", "datim_sync_mer": true, "DHIS2-Dataset-Code": "MER_R_COMMUNITY_BASED_DOD_ONLY"}, "collection_type": "Subset", "full_name": "MER Results: Community Based - DoD ONLY", "owner": "PEPFAR", "public_access": "View", "owner_type": "Organization", "type": "Collection", "id": "MER-R-Community-DoD-FY17Q4", "supported_locales": "en"}
{"name": "MER R: Medical Store", "default_locale": "en", "short_code": "MER-R-Medical-Store-FY17Q4", "external_id": "kuV7OezWYUj", "extras": {"Period": "COP16 (FY17Q4)", "datim_sync_mer": true, "DHIS2-Dataset-Code": "MER_R_MEDICAL_STORE"}, "collection_type": "Subset", "full_name": "MER Results: Medical Store", "owner": "PEPFAR", "public_access": "View", "owner_type": "Organization", "type": "Collection", "id": "MER-R-Medical-Store-FY17Q4", "supported_locales": "en"}
{"name": "MER R: Narratives (IM)", "default_locale": "en", "short_code": "MER-R-Narratives-IM-FY17Q4", "external_id": "f78MvV1k0rA", "extras": {"Period": "COP16 (FY17Q4)", "datim_sync_mer": true, "DHIS2-Dataset-Code": "MER_R_NARRATIVES_IM"}, "collection_type": "Subset", "full_name": "MER Results: Narratives (IM)", "owner": "PEPFAR", "public_access": "View", "owner_type": "Organization", "type": "Collection", "id": "MER-R-Narratives-IM-FY17Q4", "supported_locales": "en"}
{"name": "MER R: Operating Unit Level (IM)", "default_locale": "en", "short_code": "MER-R-Operating-Unit-Level-IM-FY17Q4", "external_id": "jTRF4LdklYA", "extras": {"Period": "COP16 (FY17Q4)", "datim_sync_mer": true, "DHIS2-Dataset-Code": "MER_R_OPERATING_UNIT_LEVEL_IM"}, "collection_type": "Subset", "full_name": "MER Results: Operating Unit Level (IM)", "owner": "PEPFAR", "public_access": "View", "owner_type": "Organization", "type": "Collection", "id": "MER-R-Operating-Unit-Level-IM-FY17Q4", "supported_locales": "en"}
{"name": "HC R: Narratives (USG)", "default_locale": "en", "short_code": "HC-R-Narratives-USG-FY17Q4", "external_id": "bQTvQq3pDEK", "extras": {"Period": "COP16 (FY17Q4)", "datim_sync_mer": true, "DHIS2-Dataset-Code": "HC_R_NARRATIVES_USG"}, "collection_type": "Subset", "full_name": "Host Country Results: Narratives (USG)", "owner": "PEPFAR", "public_access": "View", "owner_type": "Organization", "type": "Collection", "id": "HC-R-Narratives-USG-FY17Q4", "supported_locales": "en"}
{"name": "HC R: Operating Unit Level (USG)", "default_locale": "en", "short_code": "HC-R-Operating-Unit-Level-USG-FY17Q4", "external_id": "tFBgL95CRtN", "extras": {"Period": "COP16 (FY17Q4)", "datim_sync_mer": true, "DHIS2-Dataset-Code": "HC_R_OPERATING_UNIT_LEVEL_USG"}, "collection_type": "Subset", "full_name": "Host Country Results: Operating Unit Level (USG)", "owner": "PEPFAR", "public_access": "View", "owner_type": "Organization", "type": "Collection", "id": "HC-R-Operating-Unit-Level-USG-FY17Q4", "supported_locales": "en"}
{"name": "HC R: COP Prioritization SNU (USG)", "default_locale": "en", "short_code": "HC-R-COP-Prioritization-SNU-USG-FY17Q4", "external_id": "zNMzQjXhX7w", "extras": {"Period": "COP16 (FY17Q4)", "datim_sync_mer": true, "DHIS2-Dataset-Code": "HC_R_COP_PRIORITIZATION_SNU_USG"}, "collection_type": "Subset", "full_name": "Host Country Results: COP Prioritization SNU (USG)", "owner": "PEPFAR", "public_access": "View", "owner_type": "Organization", "type": "Collection", "id": "HC-R-COP-Prioritization-SNU-USG-FY17Q4", "supported_locales": "en"}
{"description": "Automatically generated empty repository version", "collection": "MER-R-Facility-FY17Q4", "released": true, "owner": "PEPFAR", "owner_type": "Organization", "type": "Collection Version", "id": "initial"}
{"description": "Automatically generated empty repository version", "collection": "MER-R-Community-FY17Q4", "released": true, "owner": "PEPFAR", "owner_type": "Organization", "type": "Collection Version", "id": "initial"}
{"description": "Automatically generated empty repository version", "collection": "MER-R-Facility-DoD-FY17Q4", "released": true, "owner": "PEPFAR", "owner_type": "Organization", "type": "Collection Version", "id": "initial"}
{"description": "Automatically generated empty repository version", "collection": "MER-R-Community-DoD-FY17Q4", "released": true, "owner": "PEPFAR", "owner_type": "Organization", "type": "Collection Version", "id": "initial"}
{"description": "Automatically generated empty repository version", "collection": "MER-R-Medical-Store-FY17Q4", "released": true, "owner": "PEPFAR", "owner_type": "Organization", "type": "Collection Version", "id": "initial"}
{"description": "Automatically generated empty repository version", "collection": "MER-R-Narratives-IM-FY17Q4", "released": true, "owner": "PEPFAR", "owner_type": "Organization", "type": "Collection Version", "id": "initial"}
{"description": "Automatically generated empty repository version", "collection": "MER-R-Operating-Unit-Level-IM-FY17Q4", "released": true, "owner": "PEPFAR", "owner_type": "Organization", "type": "Collection Version", "id": "initial"}
{"description": "Automatically generated empty repository version", "collection": "HC-R-Narratives-USG-FY17Q4", "released": true, "owner": "PEPFAR", "owner_type": "Organization", "type": "Collection Version", "id": "initial"}
{"description": "Automatically generated empty repository version", "collection": "HC-R-Operating-Unit-Level-USG-FY17Q4", "released": true, "owner": "PEPFAR", "owner_type": "Organization", "type": "Collection Version", "id": "initial"}
{"description": "Automatically generated empty repository version", "collection": "HC-R-COP-Prioritization-SNU-USG-FY17Q4", "released": true, "owner": "PEPFAR", "owner_type": "Organization", "type": "Collection Version", "id": "initial"}