[{"MOH_Indicator_Name": "hts_test_db_001", "Classification": "fine", "DATIM_Indicator_Category": "HTS_Contacts_Tested", "MOH_Disag_Name": "hts_test_db_001_disag", "MOH_Disag_ID": "hts_test_db_001_disag", "MOH_Indicator_ID": "hts_test_db_001", "DATIM_Disag_ID": "LokBv4egnfg", "DATIM_Indicator_ID": "HTS_INDEX_N_CS_Index_Age_Sex_Result", "DATIM_Disag_Name": "<1, Newly Tested Positives, Male", "Operation": "ADD"}, {"MOH_Indicator_Name": "htstest_db_002", "Classification": "fine", "DATIM_Indicator_Category": "HTS_Contacts_Tested", "MOH_Disag_Name": "htstest_db_002disagg", "MOH_Disag_ID": "htstest_db_002disagg", "MOH_Indicator_ID": "htstest_db_002", "DATIM_Disag_ID": "LokBv4egnfg", "DATIM_Indicator_ID": "HTS_INDEX_N_CS_Index_Age_Sex_Result", "DATIM_Disag_Name": "<1, Newly Tested Positives, Male", "Operation": "SUBTRACT"}, {"MOH_Indicator_Name": "Test101", "Classification": "fine", "DATIM_Indicator_Category": "HTS_Contacts_Tested", "MOH_Disag_Name": "10 -14 testedpostiviertemale", "MOH_Disag_ID": "jfdjfpfjs", "MOH_Indicator_ID": "2322", "DATIM_Disag_ID": "T7F0DwyrbBV", "DATIM_Indicator_ID": "HTS_INDEX_N_CS_Index_Age_Sex_Result", "DATIM_Disag_Name": "10-14, Newly Tested Positives, Female", "Operation": "ADD"}, {"DATIM_Indicator_ID": "HTS_INDEX_N_CS_Index_Age_Sex_Result", "MOH_Indicator_Name": "htscontactstested1", "DATIM_Indicator_Category": "HTS_Contacts_Tested", "Classification": "fine", "MOH_Disag_ID": "", "MOH_Indicator_ID": "htscontactstested1", "DATIM_Disag_ID": "gWPhDYzmbw5", "MOH_Disag_Name": "", "DATIM_Disag_Name": "<1, Newly Tested Positives, Female", "Operation": "ADD"}, {"MOH_Indicator_Name": "moh indicator 1 CS", "Classification": "fine", "DATIM_Indicator_Category": "HTS_Contacts_Tested", "MOH_Disag_Name": "testing_a", "MOH_Disag_ID": "testing_a", "MOH_Indicator_ID": "indicator_1_cs", "DATIM_Disag_ID": "gWPhDYzmbw5", "DATIM_Indicator_ID": "HTS_INDEX_N_CS_Index_Age_Sex_Result", "DATIM_Disag_Name": "<1, Newly Tested Positives, Female", "Operation": "ADD"}, {"DATIM_Indicator_ID": "HTS_INDEX_N_CS_Index_Age_Sex_Result", "MOH_Indicator_Name": "testing cs submission", "DATIM_Indicator_Category": "HTS_Contacts_Tested", "Classification": "fine", "MOH_Disag_ID": "", "MOH_Indicator_ID": "test_indicator_cs", "DATIM_Disag_ID": "gWPhDYzmbw5", "MOH_Disag_Name": "", "DATIM_Disag_Name": "<1, Newly Tested Positives, Female", "Operation": "ADD"}, {"DATIM_Indicator_ID": "HTS_INDEX_N_CS_Index_Age_Sex_Result", "MOH_Indicator_Name": "Testindicator2", "DATIM_Indicator_Category": "HTS_Contacts_Tested", "Classification": "fine", "MOH_Disag_ID": "", "MOH_Indicator_ID": "testindicator2", "DATIM_Disag_ID": "gcWll55WCHc", "MOH_Disag_Name": "", "DATIM_Disag_Name": "Unknown Age, New Negatives, Female", "Operation": "ADD"}, {"MOH_Indicator_Name": "htstest_db_003", "Classification": "fine", "DATIM_Indicator_Category": "HTS_Contacts_Tested", "MOH_Disag_Name": "htstest_db_002", "MOH_Disag_ID": "htstest_db_002", "MOH_Indicator_ID": "htstest_db_003", "DATIM_Disag_ID": "hLjLWfjGWpK", "DATIM_Indicator_ID": "HTS_INDEX_N_CS_Index_Age_Sex_Result", "DATIM_Disag_Name": "5-9, Newly Tested Positives, Female", "Operation": "ADD"}, {"MOH_Indicator_Name": "testdata1", "Classification": "fine", "DATIM_Indicator_Category": "HTS_Contacts_Tested", "MOH_Disag_Name": "testdata2htsindex", "MOH_Disag_ID": "testdata2htsindex", "MOH_Indicator_ID": "testdata1", "DATIM_Disag_ID": "rL9fEh5MSHf", "DATIM_Indicator_ID": "HTS_INDEX_N_CS_Index_Age_Sex_Result", "DATIM_Disag_Name": "50+, New Negatives, Male", "Operation": "ADD"}, {"DATIM_Indicator_ID": "HTS_INDEX_N_CS_Index_Age_Sex_Result", "MOH_Indicator_Name": "testing3", "DATIM_Indicator_Category": "HTS_Contacts_Tested", "Classification": "fine", "MOH_Disag_ID": "", "MOH_Indicator_ID": "testing3", "DATIM_Disag_ID": "wem5QqoRkkh", "MOH_Disag_Name": "", "DATIM_Disag_Name": "15-19, Newly Tested Positives, Female", "Operation": "ADD"}, {"MOH_Indicator_Name": "another test for cs", "Classification": "fine", "DATIM_Indicator_Category": "HTS_ER_Ward", "MOH_Disag_Name": "test disaggregation", "MOH_Disag_ID": "test-cs-disag", "MOH_Indicator_ID": "another_test", "DATIM_Disag_ID": "PPg7Yzjq0oF", "DATIM_Indicator_ID": "HTS_TST_N_CS_EW_Age_Sex_Result", "DATIM_Disag_Name": "<1, Female, Positive", "Operation": "ADD"}, {"MOH_Indicator_Name": "test again for cs", "Classification": "fine", "DATIM_Indicator_Category": "HTS_ER_Ward", "MOH_Disag_Name": "another disag name", "MOH_Disag_ID": "disag_id_again", "MOH_Indicator_ID": "test_again", "DATIM_Disag_ID": "PPg7Yzjq0oF", "DATIM_Indicator_ID": "HTS_TST_N_CS_EW_Age_Sex_Result", "DATIM_Disag_Name": "<1, Female, Positive", "Operation": "ADD"}, {"DATIM_Indicator_ID": "HTS_TST_N_CS_EW_Age_Sex_Result", "MOH_Indicator_Name": "test5", "DATIM_Indicator_Category": "HTS_ER_Ward", "Classification": "fine", "MOH_Disag_ID": "", "MOH_Indicator_ID": "test5", "DATIM_Disag_ID": "renXtk3VqTM", "MOH_Disag_Name": "", "DATIM_Disag_Name": "<1, Male, Positive", "Operation": "ADD"}, {"DATIM_Indicator_ID": "TB_PREV_N_MOH_Age_Agg_Sex_NewExistArt_HIVStatus", "MOH_Indicator_Name": "test1234", "DATIM_Indicator_Category": "TB_PREV", "Classification": "coarse", "MOH_Disag_ID": "", "MOH_Indicator_ID": "test1234", "DATIM_Disag_ID": "QKn9JHx79JO", "MOH_Disag_Name": "", "DATIM_Disag_Name": "Positive, Male, Unknown Age, Life-long ART, Already", "Operation": "ADD"}, {"DATIM_Indicator_ID": "TX_CURR_N_CS_Age_Sex_HIVStatus", "MOH_Indicator_Name": "TX_CURR_lt1_f_positive", "DATIM_Indicator_Category": "TX_CURR", "Classification": "fine", "MOH_Disag_ID": "", "MOH_Indicator_ID": "TX_CURR_lt1_f_positive", "DATIM_Disag_ID": "OMVFa98P0Yg", "MOH_Disag_Name": "", "DATIM_Disag_Name": "<1, Female, Positive", "Operation": "ADD"}, {"DATIM_Indicator_ID": "TX_NEW_N_CS_Age_Sex_HIVStatus", "MOH_Indicator_Name": "TX_NEW_lt1_f_positive", "DATIM_Indicator_Category": "TX_NEW", "Classification": "fine", "MOH_Disag_ID": "", "MOH_Indicator_ID": "TX_NEW_lt1_f_positive", "DATIM_Disag_ID": "OMVFa98P0Yg", "MOH_Disag_Name": "", "DATIM_Disag_Name": "<1, Female, Positive", "Operation": "ADD"}]